{
    "results": [
        {
            "siren": "519239677",
            "nom_complet": "PUBLIC ACTIF",
            "nom_raison_sociale": "PUBLIC ACTIF",
            "sigle": null,
            "nombre_etablissements": 5,
            "nombre_etablissements_ouverts": 2,
            "siege": {
                "activite_principale": "73.11Z",
                "activite_principale_naf25": "73.11Y",
                "activite_principale_registre_metier": null,
                "annee_tranche_effectif_salarie": "2023",
                "adresse": "24 RUE LAURE DIEBOLD 69009 LYON",
                "caractere_employeur": "O",
                "cedex": null,
                "code_pays_etranger": null,
                "code_postal": "69009",
                "commune": "69389",
                "complement_adresse": null,
                "coordonnees": "45.77830379,4.8000979507",
                "date_creation": "2022-10-01",
                "date_debut_activite": "2022-10-01",
                "date_fermeture": null,
                "date_mise_a_jour": null,
                "date_mise_a_jour_insee": "2025-12-05T16:24:38",
                "departement": "69",
                "distribution_speciale": null,
                "epci": "200046977",
                "est_siege": true,
                "etat_administratif": "A",
                "geo_adresse": null,
                "geo_id": null,
                "indice_repetition": null,
                "latitude": "45.77830379",
                "libelle_cedex": null,
                "libelle_commune": "LYON",
                "libelle_commune_etranger": null,
                "libelle_pays_etranger": null,
                "libelle_voie": "LAURE DIEBOLD",
                "liste_enseignes": null,
                "liste_finess": null,
                "liste_id_bio": null,
                "liste_idcc": [
                    "0086"
                ],
                "liste_id_organisme_formation": null,
                "liste_rge": null,
                "liste_uai": null,
                "longitude": "4.8000979507",
                "nom_commercial": null,
                "numero_voie": "24",
                "dernier_numero_voie": null,
                "region": "84",
                "siret": "51923967700056",
                "statut_diffusion_etablissement": "O",
                "tranche_effectif_salarie": "03",
                "type_voie": "RUE"
            },
            "activite_principale": "73.11Z",
            "activite_principale_naf25": "73.11Y",
            "categorie_entreprise": "PME",
            "caractere_employeur": null,
            "annee_categorie_entreprise": "2023",
            "date_creation": "2010-01-05",
            "date_fermeture": null,
            "date_mise_a_jour": "2026-06-04T10:07:56",
            "date_mise_a_jour_insee": "2025-12-06T05:37:48",
            "date_mise_a_jour_rne": "2024-05-19T17:01:20",
            "dirigeants": [
                {
                    "siren": "818056624",
                    "denomination": "AS SOCIAL AS POSSIBLE",
                    "qualite": "Pr\u00e9sident de SAS",
                    "type_dirigeant": "personne morale"
                }
            ],
            "etat_administratif": "A",
            "nature_juridique": "5710",
            "section_activite_principale": "M",
            "tranche_effectif_salarie": "11",
            "annee_tranche_effectif_salarie": "2023",
            "statut_diffusion": "O",
            "matching_etablissements": [
                {
                    "activite_principale": "73.11Z",
                    "activite_principale_naf25": "73.11Y",
                    "ancien_siege": false,
                    "annee_tranche_effectif_salarie": "2023",
                    "adresse": "15 RUE DU FAUBOURG MONTMARTRE 75009 PARIS",
                    "caractere_employeur": "O",
                    "code_postal": "75009",
                    "commune": "75109",
                    "date_creation": "2018-09-03",
                    "date_debut_activite": "2018-09-03",
                    "date_fermeture": null,
                    "epci": "200054781",
                    "est_siege": false,
                    "etat_administratif": "A",
                    "geo_id": null,
                    "latitude": "48.872544167",
                    "libelle_commune": "PARIS",
                    "liste_enseignes": null,
                    "liste_finess": null,
                    "liste_id_bio": null,
                    "liste_idcc": [
                        "0086"
                    ],
                    "liste_id_organisme_formation": null,
                    "liste_rge": null,
                    "liste_uai": null,
                    "longitude": "2.3428031513",
                    "nom_commercial": null,
                    "region": "11",
                    "siret": "51923967700031",
                    "statut_diffusion_etablissement": "O",
                    "tranche_effectif_salarie": "03"
                },
                {
                    "activite_principale": "73.11Z",
                    "activite_principale_naf25": "73.11Y",
                    "ancien_siege": false,
                    "annee_tranche_effectif_salarie": "2023",
                    "adresse": "24 RUE LAURE DIEBOLD 69009 LYON",
                    "caractere_employeur": "O",
                    "code_postal": "69009",
                    "commune": "69389",
                    "date_creation": "2022-10-01",
                    "date_debut_activite": "2022-10-01",
                    "date_fermeture": null,
                    "epci": "200046977",
                    "est_siege": true,
                    "etat_administratif": "A",
                    "geo_id": null,
                    "latitude": "45.77830379",
                    "libelle_commune": "LYON",
                    "liste_enseignes": null,
                    "liste_finess": null,
                    "liste_id_bio": null,
                    "liste_idcc": [
                        "0086"
                    ],
                    "liste_id_organisme_formation": null,
                    "liste_rge": null,
                    "liste_uai": null,
                    "longitude": "4.8000979507",
                    "nom_commercial": null,
                    "region": "84",
                    "siret": "51923967700056",
                    "statut_diffusion_etablissement": "O",
                    "tranche_effectif_salarie": "03"
                },
                {
                    "activite_principale": "73.11Z",
                    "activite_principale_naf25": null,
                    "ancien_siege": true,
                    "annee_tranche_effectif_salarie": null,
                    "adresse": "LALOUET 69620 TERNAND",
                    "caractere_employeur": "O",
                    "code_postal": "69620",
                    "commune": "69245",
                    "date_creation": "2010-01-05",
                    "date_debut_activite": "2013-08-30",
                    "date_fermeture": "2013-08-30",
                    "epci": "200040574",
                    "est_siege": false,
                    "etat_administratif": "F",
                    "geo_id": null,
                    "latitude": null,
                    "libelle_commune": "TERNAND",
                    "liste_enseignes": null,
                    "liste_finess": null,
                    "liste_id_bio": null,
                    "liste_idcc": null,
                    "liste_id_organisme_formation": null,
                    "liste_rge": null,
                    "liste_uai": null,
                    "longitude": null,
                    "nom_commercial": null,
                    "region": "84",
                    "siret": "51923967700015",
                    "statut_diffusion_etablissement": "O",
                    "tranche_effectif_salarie": "NN"
                },
                {
                    "activite_principale": "73.11Z",
                    "activite_principale_naf25": null,
                    "ancien_siege": false,
                    "annee_tranche_effectif_salarie": null,
                    "adresse": "14 CHEMIN DU JUBIN 69570 DARDILLY",
                    "caractere_employeur": "O",
                    "code_postal": "69570",
                    "commune": "69072",
                    "date_creation": "2013-08-30",
                    "date_debut_activite": "2018-04-28",
                    "date_fermeture": "2018-04-28",
                    "epci": "200046977",
                    "est_siege": false,
                    "etat_administratif": "F",
                    "geo_id": null,
                    "latitude": "45.8121323864654",
                    "libelle_commune": "DARDILLY",
                    "liste_enseignes": null,
                    "liste_finess": null,
                    "liste_id_bio": null,
                    "liste_idcc": null,
                    "liste_id_organisme_formation": null,
                    "liste_rge": null,
                    "liste_uai": null,
                    "longitude": "4.76232058334483",
                    "nom_commercial": null,
                    "region": "84",
                    "siret": "51923967700023",
                    "statut_diffusion_etablissement": "O",
                    "tranche_effectif_salarie": "NN"
                },
                {
                    "activite_principale": "73.11Z",
                    "activite_principale_naf25": null,
                    "ancien_siege": false,
                    "annee_tranche_effectif_salarie": null,
                    "adresse": "25 RUE SAINT SIMON 69009 LYON",
                    "caractere_employeur": "O",
                    "code_postal": "69009",
                    "commune": "69389",
                    "date_creation": "2018-04-28",
                    "date_debut_activite": "2022-10-01",
                    "date_fermeture": "2022-10-01",
                    "epci": "200046977",
                    "est_siege": false,
                    "etat_administratif": "F",
                    "geo_id": null,
                    "latitude": "45.776702364",
                    "libelle_commune": "LYON",
                    "liste_enseignes": null,
                    "liste_finess": null,
                    "liste_id_bio": null,
                    "liste_idcc": null,
                    "liste_id_organisme_formation": null,
                    "liste_rge": null,
                    "liste_uai": null,
                    "longitude": "4.7969807707",
                    "nom_commercial": null,
                    "region": "84",
                    "siret": "51923967700049",
                    "statut_diffusion_etablissement": "O",
                    "tranche_effectif_salarie": "NN"
                }
            ],
            "finances": {
                "2024": {
                    "ca": 0,
                    "resultat_net": 213413
                }
            },
            "complements": {
                "collectivite_territoriale": null,
                "convention_collective_renseignee": true,
                "liste_idcc": [
                    "0086"
                ],
                "liste_finess_juridique": null,
                "egapro_renseignee": false,
                "est_achats_responsables": false,
                "est_alim_confiance": false,
                "est_association": false,
                "est_avocat": false,
                "est_bio": false,
                "est_entrepreneur_individuel": false,
                "est_entrepreneur_spectacle": false,
                "est_ess": false,
                "est_finess": false,
                "est_organisme_formation": false,
                "est_qualiopi": false,
                "liste_id_organisme_formation": null,
                "est_rge": false,
                "est_siae": false,
                "est_societe_mission": false,
                "est_uai": false,
                "est_patrimoine_vivant": false,
                "bilan_ges_renseigne": false,
                "identifiant_association": null,
                "statut_entrepreneur_spectacle": null,
                "type_siae": null,
                "a_aide_minimis": false,
                "a_aide_ademe": false,
                "est_administration": false,
                "est_service_public": null,
                "est_l100_3": null
            }
        },
        {
            "siren": "853391704",
            "nom_complet": "ACTIF CONSTRUCTION BATIMENT ET TRAVAUX PUBLICS (ACBTP)",
            "nom_raison_sociale": "ACTIF CONSTRUCTION BATIMENT ET TRAVAUX PUBLICS",
            "sigle": "ACBTP",
            "nombre_etablissements": 1,
            "nombre_etablissements_ouverts": 1,
            "siege": {
                "activite_principale": "41.20B",
                "activite_principale_naf25": "41.00H",
                "activite_principale_registre_metier": "4120BA",
                "annee_tranche_effectif_salarie": null,
                "adresse": "KAWENI 226 IMPASSE VILVILINI 97600 MAMOUDZOU",
                "caractere_employeur": "O",
                "cedex": null,
                "code_pays_etranger": null,
                "code_postal": "97600",
                "commune": "97611",
                "complement_adresse": "KAWENI",
                "coordonnees": "-12.763868023930483,45.22883002284311",
                "date_creation": "2019-08-26",
                "date_debut_activite": "2019-08-26",
                "date_fermeture": null,
                "date_mise_a_jour": null,
                "date_mise_a_jour_insee": "2025-12-05T22:22:13",
                "departement": "976",
                "distribution_speciale": null,
                "epci": "200060457",
                "est_siege": true,
                "etat_administratif": "A",
                "geo_adresse": null,
                "geo_id": null,
                "indice_repetition": null,
                "latitude": "-12.763868023930483",
                "libelle_cedex": null,
                "libelle_commune": "MAMOUDZOU",
                "libelle_commune_etranger": null,
                "libelle_pays_etranger": null,
                "libelle_voie": "VILVILINI",
                "liste_enseignes": null,
                "liste_finess": null,
                "liste_id_bio": null,
                "liste_idcc": [
                    "9999"
                ],
                "liste_id_organisme_formation": null,
                "liste_rge": null,
                "liste_uai": null,
                "longitude": "45.22883002284311",
                "nom_commercial": null,
                "numero_voie": "226",
                "dernier_numero_voie": null,
                "region": "06",
                "siret": "85339170400014",
                "statut_diffusion_etablissement": "O",
                "tranche_effectif_salarie": "NN",
                "type_voie": "IMPASSE"
            },
            "activite_principale": "41.20B",
            "activite_principale_naf25": "41.00H",
            "categorie_entreprise": "PME",
            "caractere_employeur": null,
            "annee_categorie_entreprise": "2023",
            "date_creation": "2019-08-26",
            "date_fermeture": null,
            "date_mise_a_jour": "2026-06-04T11:00:57",
            "date_mise_a_jour_insee": "2025-12-06T05:27:41",
            "date_mise_a_jour_rne": "2024-05-19T17:01:20",
            "dirigeants": [
                {
                    "nom": "AMBOUDI",
                    "prenoms": "MADI",
                    "annee_de_naissance": "1980",
                    "date_de_naissance": "1980-04",
                    "qualite": "G\u00e9rant",
                    "nationalite": null,
                    "type_dirigeant": "personne physique"
                }
            ],
            "etat_administratif": "A",
            "nature_juridique": "5499",
            "section_activite_principale": "F",
            "tranche_effectif_salarie": "NN",
            "annee_tranche_effectif_salarie": null,
            "statut_diffusion": "O",
            "matching_etablissements": [
                {
                    "activite_principale": "41.20B",
                    "activite_principale_naf25": "41.00H",
                    "ancien_siege": false,
                    "annee_tranche_effectif_salarie": null,
                    "adresse": "KAWENI 226 IMPASSE VILVILINI 97600 MAMOUDZOU",
                    "caractere_employeur": "O",
                    "code_postal": "97600",
                    "commune": "97611",
                    "date_creation": "2019-08-26",
                    "date_debut_activite": "2019-08-26",
                    "date_fermeture": null,
                    "epci": "200060457",
                    "est_siege": true,
                    "etat_administratif": "A",
                    "geo_id": null,
                    "latitude": "-12.763868023930483",
                    "libelle_commune": "MAMOUDZOU",
                    "liste_enseignes": null,
                    "liste_finess": null,
                    "liste_id_bio": null,
                    "liste_idcc": [
                        "9999"
                    ],
                    "liste_id_organisme_formation": null,
                    "liste_rge": null,
                    "liste_uai": null,
                    "longitude": "45.22883002284311",
                    "nom_commercial": null,
                    "region": "06",
                    "siret": "85339170400014",
                    "statut_diffusion_etablissement": "O",
                    "tranche_effectif_salarie": "NN"
                }
            ],
            "finances": {
                "2024": {
                    "ca": 0,
                    "resultat_net": 151596
                }
            },
            "complements": {
                "collectivite_territoriale": null,
                "convention_collective_renseignee": true,
                "liste_idcc": [
                    "9999"
                ],
                "liste_finess_juridique": null,
                "egapro_renseignee": false,
                "est_achats_responsables": false,
                "est_alim_confiance": false,
                "est_association": false,
                "est_avocat": false,
                "est_bio": false,
                "est_entrepreneur_individuel": false,
                "est_entrepreneur_spectacle": false,
                "est_ess": false,
                "est_finess": false,
                "est_organisme_formation": false,
                "est_qualiopi": false,
                "liste_id_organisme_formation": null,
                "est_rge": false,
                "est_siae": false,
                "est_societe_mission": false,
                "est_uai": false,
                "est_patrimoine_vivant": false,
                "bilan_ges_renseigne": false,
                "identifiant_association": null,
                "statut_entrepreneur_spectacle": null,
                "type_siae": null,
                "a_aide_minimis": false,
                "a_aide_ademe": false,
                "est_administration": false,
                "est_service_public": null,
                "est_l100_3": null
            }
        },
        {
            "siren": "810930651",
            "nom_complet": "COORDINATION SYNDICALE DEPARTEMENTALE CGT DES PERSONNELS ACTIFS ET RETRAITES DES SERVICES PUBLICS DU FINISTERE",
            "nom_raison_sociale": "COORDINATION SYNDICALE DEPARTEMENTALE CGT DES PERSONNELS ACTIFS ET RETRAITES DES SERVICES PUBLICS DU FINISTERE",
            "sigle": null,
            "nombre_etablissements": 1,
            "nombre_etablissements_ouverts": 1,
            "siege": {
                "activite_principale": "94.20Z",
                "activite_principale_naf25": "94.20Y",
                "activite_principale_registre_metier": null,
                "annee_tranche_effectif_salarie": null,
                "adresse": "MAISON DU PEUPLE 5 PLACE EDOUARD MAZE 29200 BREST",
                "caractere_employeur": "N",
                "cedex": null,
                "code_pays_etranger": null,
                "code_postal": "29200",
                "commune": "29019",
                "complement_adresse": "MAISON DU PEUPLE",
                "coordonnees": "48.392476445,-4.491008465",
                "date_creation": "2008-02-27",
                "date_debut_activite": "2008-02-27",
                "date_fermeture": null,
                "date_mise_a_jour": null,
                "date_mise_a_jour_insee": "2025-12-05T17:47:27",
                "departement": "29",
                "distribution_speciale": null,
                "epci": "242900314",
                "est_siege": true,
                "etat_administratif": "A",
                "geo_adresse": null,
                "geo_id": null,
                "indice_repetition": null,
                "latitude": "48.392476445",
                "libelle_cedex": null,
                "libelle_commune": "BREST",
                "libelle_commune_etranger": null,
                "libelle_pays_etranger": null,
                "libelle_voie": "EDOUARD MAZE",
                "liste_enseignes": null,
                "liste_finess": null,
                "liste_id_bio": null,
                "liste_idcc": null,
                "liste_id_organisme_formation": null,
                "liste_rge": null,
                "liste_uai": null,
                "longitude": "-4.491008465",
                "nom_commercial": null,
                "numero_voie": "5",
                "dernier_numero_voie": null,
                "region": "53",
                "siret": "81093065100015",
                "statut_diffusion_etablissement": "O",
                "tranche_effectif_salarie": "NN",
                "type_voie": "PLACE"
            },
            "activite_principale": "94.20Z",
            "activite_principale_naf25": "94.20Y",
            "categorie_entreprise": null,
            "caractere_employeur": null,
            "annee_categorie_entreprise": null,
            "date_creation": "2008-02-27",
            "date_fermeture": null,
            "date_mise_a_jour": "2026-06-04T10:38:42",
            "date_mise_a_jour_insee": "2025-12-06T07:43:55",
            "date_mise_a_jour_rne": null,
            "dirigeants": [],
            "etat_administratif": "A",
            "nature_juridique": "8410",
            "section_activite_principale": "S",
            "tranche_effectif_salarie": "NN",
            "annee_tranche_effectif_salarie": null,
            "statut_diffusion": "O",
            "matching_etablissements": [
                {
                    "activite_principale": "94.20Z",
                    "activite_principale_naf25": "94.20Y",
                    "ancien_siege": false,
                    "annee_tranche_effectif_salarie": null,
                    "adresse": "MAISON DU PEUPLE 5 PLACE EDOUARD MAZE 29200 BREST",
                    "caractere_employeur": "N",
                    "code_postal": "29200",
                    "commune": "29019",
                    "date_creation": "2008-02-27",
                    "date_debut_activite": "2008-02-27",
                    "date_fermeture": null,
                    "epci": "242900314",
                    "est_siege": true,
                    "etat_administratif": "A",
                    "geo_id": null,
                    "latitude": "48.392476445",
                    "libelle_commune": "BREST",
                    "liste_enseignes": null,
                    "liste_finess": null,
                    "liste_id_bio": null,
                    "liste_idcc": null,
                    "liste_id_organisme_formation": null,
                    "liste_rge": null,
                    "liste_uai": null,
                    "longitude": "-4.491008465",
                    "nom_commercial": null,
                    "region": "53",
                    "siret": "81093065100015",
                    "statut_diffusion_etablissement": "O",
                    "tranche_effectif_salarie": "NN"
                }
            ],
            "finances": null,
            "complements": {
                "collectivite_territoriale": null,
                "convention_collective_renseignee": false,
                "liste_idcc": null,
                "liste_finess_juridique": null,
                "egapro_renseignee": false,
                "est_achats_responsables": false,
                "est_alim_confiance": false,
                "est_association": false,
                "est_avocat": false,
                "est_bio": false,
                "est_entrepreneur_individuel": false,
                "est_entrepreneur_spectacle": false,
                "est_ess": false,
                "est_finess": false,
                "est_organisme_formation": false,
                "est_qualiopi": false,
                "liste_id_organisme_formation": null,
                "est_rge": false,
                "est_siae": false,
                "est_societe_mission": false,
                "est_uai": false,
                "est_patrimoine_vivant": false,
                "bilan_ges_renseigne": false,
                "identifiant_association": null,
                "statut_entrepreneur_spectacle": null,
                "type_siae": null,
                "a_aide_minimis": false,
                "a_aide_ademe": false,
                "est_administration": false,
                "est_service_public": null,
                "est_l100_3": null
            }
        },
        {
            "siren": "893493619",
            "nom_complet": "SYNDICAT CGT DES FONCTIONNAIRES TERRITORIAUX ACTIFS ET DES RETRAITES DES ETABLISSEMENTS PUBLICS ET PRIVES AUBERVILLIERS (CGT)",
            "nom_raison_sociale": "SYNDICAT CGT DES FONCTIONNAIRES TERRITORIAUX ACTIFS ET DES RETRAITES DES ETABLISSEMENTS PUBLICS ET PRIVES AUBERVILLIERS",
            "sigle": "CGT",
            "nombre_etablissements": 1,
            "nombre_etablissements_ouverts": 1,
            "siege": {
                "activite_principale": "94.20Z",
                "activite_principale_naf25": "94.20Y",
                "activite_principale_registre_metier": null,
                "annee_tranche_effectif_salarie": null,
                "adresse": "CTM - BAT ADMINISTRATIF - BUREAU 228 72 RUE HENRI BARBUSSE 93300 AUBERVILLIERS",
                "caractere_employeur": "N",
                "cedex": null,
                "code_pays_etranger": null,
                "code_postal": "93300",
                "commune": "93001",
                "complement_adresse": "CTM - BAT ADMINISTRATIF - BUREAU 228",
                "coordonnees": "48.906814202,2.3914303128",
                "date_creation": "1947-01-04",
                "date_debut_activite": "1947-01-04",
                "date_fermeture": null,
                "date_mise_a_jour": null,
                "date_mise_a_jour_insee": "2025-12-05T17:24:10",
                "departement": "93",
                "distribution_speciale": null,
                "epci": "200054781",
                "est_siege": true,
                "etat_administratif": "A",
                "geo_adresse": null,
                "geo_id": null,
                "indice_repetition": null,
                "latitude": "48.906814202",
                "libelle_cedex": null,
                "libelle_commune": "AUBERVILLIERS",
                "libelle_commune_etranger": null,
                "libelle_pays_etranger": null,
                "libelle_voie": "HENRI BARBUSSE",
                "liste_enseignes": null,
                "liste_finess": null,
                "liste_id_bio": null,
                "liste_idcc": null,
                "liste_id_organisme_formation": null,
                "liste_rge": null,
                "liste_uai": null,
                "longitude": "2.3914303128",
                "nom_commercial": null,
                "numero_voie": "72",
                "dernier_numero_voie": null,
                "region": "11",
                "siret": "89349361900017",
                "statut_diffusion_etablissement": "O",
                "tranche_effectif_salarie": "NN",
                "type_voie": "RUE"
            },
            "activite_principale": "94.20Z",
            "activite_principale_naf25": "94.20Y",
            "categorie_entreprise": null,
            "caractere_employeur": null,
            "annee_categorie_entreprise": null,
            "date_creation": "1947-01-04",
            "date_fermeture": null,
            "date_mise_a_jour": "2026-06-04T11:10:13",
            "date_mise_a_jour_insee": "2025-12-06T08:43:45",
            "date_mise_a_jour_rne": null,
            "dirigeants": [],
            "etat_administratif": "A",
            "nature_juridique": "8410",
            "section_activite_principale": "S",
            "tranche_effectif_salarie": "NN",
            "annee_tranche_effectif_salarie": null,
            "statut_diffusion": "O",
            "matching_etablissements": [
                {
                    "activite_principale": "94.20Z",
                    "activite_principale_naf25": "94.20Y",
                    "ancien_siege": false,
                    "annee_tranche_effectif_salarie": null,
                    "adresse": "CTM - BAT ADMINISTRATIF - BUREAU 228 72 RUE HENRI BARBUSSE 93300 AUBERVILLIERS",
                    "caractere_employeur": "N",
                    "code_postal": "93300",
                    "commune": "93001",
                    "date_creation": "1947-01-04",
                    "date_debut_activite": "1947-01-04",
                    "date_fermeture": null,
                    "epci": "200054781",
                    "est_siege": true,
                    "etat_administratif": "A",
                    "geo_id": null,
                    "latitude": "48.906814202",
                    "libelle_commune": "AUBERVILLIERS",
                    "liste_enseignes": null,
                    "liste_finess": null,
                    "liste_id_bio": null,
                    "liste_idcc": null,
                    "liste_id_organisme_formation": null,
                    "liste_rge": null,
                    "liste_uai": null,
                    "longitude": "2.3914303128",
                    "nom_commercial": null,
                    "region": "11",
                    "siret": "89349361900017",
                    "statut_diffusion_etablissement": "O",
                    "tranche_effectif_salarie": "NN"
                }
            ],
            "finances": null,
            "complements": {
                "collectivite_territoriale": null,
                "convention_collective_renseignee": false,
                "liste_idcc": null,
                "liste_finess_juridique": null,
                "egapro_renseignee": false,
                "est_achats_responsables": false,
                "est_alim_confiance": false,
                "est_association": false,
                "est_avocat": false,
                "est_bio": false,
                "est_entrepreneur_individuel": false,
                "est_entrepreneur_spectacle": false,
                "est_ess": false,
                "est_finess": false,
                "est_organisme_formation": false,
                "est_qualiopi": false,
                "liste_id_organisme_formation": null,
                "est_rge": false,
                "est_siae": false,
                "est_societe_mission": false,
                "est_uai": false,
                "est_patrimoine_vivant": false,
                "bilan_ges_renseigne": false,
                "identifiant_association": null,
                "statut_entrepreneur_spectacle": null,
                "type_siae": null,
                "a_aide_minimis": false,
                "a_aide_ademe": false,
                "est_administration": false,
                "est_service_public": null,
                "est_l100_3": null
            }
        },
        {
            "siren": "831281126",
            "nom_complet": "SYNDICAT CGT DES TERRITORIAUX ACTIFS ET RETRAITES DES ETABLISSEMENTS PUBLICS COMMUNAUX DE NOISY LE GRAND",
            "nom_raison_sociale": "SYNDICAT CGT DES TERRITORIAUX ACTIFS ET RETRAITES DES ETABLISSEMENTS PUBLICS COMMUNAUX DE NOISY LE GRAND",
            "sigle": null,
            "nombre_etablissements": 1,
            "nombre_etablissements_ouverts": 1,
            "siege": {
                "activite_principale": "94.20Z",
                "activite_principale_naf25": "94.20Y",
                "activite_principale_registre_metier": null,
                "annee_tranche_effectif_salarie": null,
                "adresse": "10 RUE ROUGET DE LISLE 93160 NOISY-LE-GRAND",
                "caractere_employeur": "N",
                "cedex": null,
                "code_pays_etranger": null,
                "code_postal": "93160",
                "commune": "93051",
                "complement_adresse": null,
                "coordonnees": "48.848670206,2.5651672588",
                "date_creation": "1998-02-19",
                "date_debut_activite": "1998-02-19",
                "date_fermeture": null,
                "date_mise_a_jour": null,
                "date_mise_a_jour_insee": "2025-12-06T00:33:26",
                "departement": "93",
                "distribution_speciale": null,
                "epci": "200054781",
                "est_siege": true,
                "etat_administratif": "A",
                "geo_adresse": null,
                "geo_id": null,
                "indice_repetition": null,
                "latitude": "48.848670206",
                "libelle_cedex": null,
                "libelle_commune": "NOISY-LE-GRAND",
                "libelle_commune_etranger": null,
                "libelle_pays_etranger": null,
                "libelle_voie": "ROUGET DE LISLE",
                "liste_enseignes": null,
                "liste_finess": null,
                "liste_id_bio": null,
                "liste_idcc": null,
                "liste_id_organisme_formation": null,
                "liste_rge": null,
                "liste_uai": null,
                "longitude": "2.5651672588",
                "nom_commercial": null,
                "numero_voie": "10",
                "dernier_numero_voie": null,
                "region": "11",
                "siret": "83128112600019",
                "statut_diffusion_etablissement": "O",
                "tranche_effectif_salarie": "NN",
                "type_voie": "RUE"
            },
            "activite_principale": "94.20Z",
            "activite_principale_naf25": "94.20Y",
            "categorie_entreprise": null,
            "caractere_employeur": null,
            "annee_categorie_entreprise": null,
            "date_creation": "1998-02-19",
            "date_fermeture": null,
            "date_mise_a_jour": "2026-06-04T10:49:29",
            "date_mise_a_jour_insee": "2025-12-06T06:20:18",
            "date_mise_a_jour_rne": null,
            "dirigeants": [],
            "etat_administratif": "A",
            "nature_juridique": "8410",
            "section_activite_principale": "S",
            "tranche_effectif_salarie": "NN",
            "annee_tranche_effectif_salarie": null,
            "statut_diffusion": "O",
            "matching_etablissements": [
                {
                    "activite_principale": "94.20Z",
                    "activite_principale_naf25": "94.20Y",
                    "ancien_siege": false,
                    "annee_tranche_effectif_salarie": null,
                    "adresse": "10 RUE ROUGET DE LISLE 93160 NOISY-LE-GRAND",
                    "caractere_employeur": "N",
                    "code_postal": "93160",
                    "commune": "93051",
                    "date_creation": "1998-02-19",
                    "date_debut_activite": "1998-02-19",
                    "date_fermeture": null,
                    "epci": "200054781",
                    "est_siege": true,
                    "etat_administratif": "A",
                    "geo_id": null,
                    "latitude": "48.848670206",
                    "libelle_commune": "NOISY-LE-GRAND",
                    "liste_enseignes": null,
                    "liste_finess": null,
                    "liste_id_bio": null,
                    "liste_idcc": null,
                    "liste_id_organisme_formation": null,
                    "liste_rge": null,
                    "liste_uai": null,
                    "longitude": "2.5651672588",
                    "nom_commercial": null,
                    "region": "11",
                    "siret": "83128112600019",
                    "statut_diffusion_etablissement": "O",
                    "tranche_effectif_salarie": "NN"
                }
            ],
            "finances": null,
            "complements": {
                "collectivite_territoriale": null,
                "convention_collective_renseignee": false,
                "liste_idcc": null,
                "liste_finess_juridique": null,
                "egapro_renseignee": false,
                "est_achats_responsables": false,
                "est_alim_confiance": false,
                "est_association": false,
                "est_avocat": false,
                "est_bio": false,
                "est_entrepreneur_individuel": false,
                "est_entrepreneur_spectacle": false,
                "est_ess": false,
                "est_finess": false,
                "est_organisme_formation": false,
                "est_qualiopi": false,
                "liste_id_organisme_formation": null,
                "est_rge": false,
                "est_siae": false,
                "est_societe_mission": false,
                "est_uai": false,
                "est_patrimoine_vivant": false,
                "bilan_ges_renseigne": false,
                "identifiant_association": null,
                "statut_entrepreneur_spectacle": null,
                "type_siae": null,
                "a_aide_minimis": false,
                "a_aide_ademe": false,
                "est_administration": false,
                "est_service_public": null,
                "est_l100_3": null
            }
        },
        {
            "siren": "848325163",
            "nom_complet": "SYNDICAT CGT DES FONCTIONNAIRES ET AGENTS TERRITORIAUX ACTIFS ET RETRAITES DES ETABLISSEMENTS PUBLICS ET PRIVES DE LA VI",
            "nom_raison_sociale": "SYNDICAT CGT DES FONCTIONNAIRES ET AGENTS TERRITORIAUX ACTIFS ET RETRAITES DES ETABLISSEMENTS PUBLICS ET PRIVES DE LA VI",
            "sigle": null,
            "nombre_etablissements": 1,
            "nombre_etablissements_ouverts": 1,
            "siege": {
                "activite_principale": "94.20Z",
                "activite_principale_naf25": "94.20Y",
                "activite_principale_registre_metier": null,
                "annee_tranche_effectif_salarie": null,
                "adresse": "CRAN GEVRIER 29 RUE DE LA CRETE - ANNECY 74000 ANNECY",
                "caractere_employeur": "N",
                "cedex": null,
                "code_pays_etranger": null,
                "code_postal": "74000",
                "commune": "74010",
                "complement_adresse": "CRAN GEVRIER",
                "coordonnees": "45.910457644,6.1091934228",
                "date_creation": "2018-04-26",
                "date_debut_activite": "2018-04-26",
                "date_fermeture": null,
                "date_mise_a_jour": null,
                "date_mise_a_jour_insee": "2025-12-05T18:38:42",
                "departement": "74",
                "distribution_speciale": null,
                "epci": "200066793",
                "est_siege": true,
                "etat_administratif": "A",
                "geo_adresse": null,
                "geo_id": null,
                "indice_repetition": null,
                "latitude": "45.910457644",
                "libelle_cedex": null,
                "libelle_commune": "ANNECY",
                "libelle_commune_etranger": null,
                "libelle_pays_etranger": null,
                "libelle_voie": "DE LA CRETE - ANNECY",
                "liste_enseignes": null,
                "liste_finess": null,
                "liste_id_bio": null,
                "liste_idcc": null,
                "liste_id_organisme_formation": null,
                "liste_rge": null,
                "liste_uai": null,
                "longitude": "6.1091934228",
                "nom_commercial": null,
                "numero_voie": "29",
                "dernier_numero_voie": null,
                "region": "84",
                "siret": "84832516300014",
                "statut_diffusion_etablissement": "O",
                "tranche_effectif_salarie": "NN",
                "type_voie": "RUE"
            },
            "activite_principale": "94.20Z",
            "activite_principale_naf25": "94.20Y",
            "categorie_entreprise": null,
            "caractere_employeur": null,
            "annee_categorie_entreprise": null,
            "date_creation": "2018-04-26",
            "date_fermeture": null,
            "date_mise_a_jour": "2026-06-04T10:57:48",
            "date_mise_a_jour_insee": "2025-12-06T09:32:08",
            "date_mise_a_jour_rne": null,
            "dirigeants": [],
            "etat_administratif": "A",
            "nature_juridique": "8410",
            "section_activite_principale": "S",
            "tranche_effectif_salarie": "NN",
            "annee_tranche_effectif_salarie": null,
            "statut_diffusion": "O",
            "matching_etablissements": [
                {
                    "activite_principale": "94.20Z",
                    "activite_principale_naf25": "94.20Y",
                    "ancien_siege": false,
                    "annee_tranche_effectif_salarie": null,
                    "adresse": "CRAN GEVRIER 29 RUE DE LA CRETE - ANNECY 74000 ANNECY",
                    "caractere_employeur": "N",
                    "code_postal": "74000",
                    "commune": "74010",
                    "date_creation": "2018-04-26",
                    "date_debut_activite": "2018-04-26",
                    "date_fermeture": null,
                    "epci": "200066793",
                    "est_siege": true,
                    "etat_administratif": "A",
                    "geo_id": null,
                    "latitude": "45.910457644",
                    "libelle_commune": "ANNECY",
                    "liste_enseignes": null,
                    "liste_finess": null,
                    "liste_id_bio": null,
                    "liste_idcc": null,
                    "liste_id_organisme_formation": null,
                    "liste_rge": null,
                    "liste_uai": null,
                    "longitude": "6.1091934228",
                    "nom_commercial": null,
                    "region": "84",
                    "siret": "84832516300014",
                    "statut_diffusion_etablissement": "O",
                    "tranche_effectif_salarie": "NN"
                }
            ],
            "finances": null,
            "complements": {
                "collectivite_territoriale": null,
                "convention_collective_renseignee": false,
                "liste_idcc": null,
                "liste_finess_juridique": null,
                "egapro_renseignee": false,
                "est_achats_responsables": false,
                "est_alim_confiance": false,
                "est_association": false,
                "est_avocat": false,
                "est_bio": false,
                "est_entrepreneur_individuel": false,
                "est_entrepreneur_spectacle": false,
                "est_ess": false,
                "est_finess": false,
                "est_organisme_formation": false,
                "est_qualiopi": false,
                "liste_id_organisme_formation": null,
                "est_rge": false,
                "est_siae": false,
                "est_societe_mission": false,
                "est_uai": false,
                "est_patrimoine_vivant": false,
                "bilan_ges_renseigne": false,
                "identifiant_association": null,
                "statut_entrepreneur_spectacle": null,
                "type_siae": null,
                "a_aide_minimis": false,
                "a_aide_ademe": false,
                "est_administration": false,
                "est_service_public": null,
                "est_l100_3": null
            }
        },
        {
            "siren": "910548148",
            "nom_complet": "SYNDICAT CGT DES FONCTIONNAIRES ET AGENTS TERRITORIAUX ACTIFS ET RETRAITES DES ETABLISSEMENTS PUBLICS  PRIVES DE DRAVEIL",
            "nom_raison_sociale": "SYNDICAT CGT DES FONCTIONNAIRES ET AGENTS TERRITORIAUX ACTIFS ET RETRAITES DES ETABLISSEMENTS PUBLICS  PRIVES DE DRAVEIL",
            "sigle": null,
            "nombre_etablissements": 1,
            "nombre_etablissements_ouverts": 1,
            "siege": {
                "activite_principale": "94.20Z",
                "activite_principale_naf25": "94.20Y",
                "activite_principale_registre_metier": null,
                "annee_tranche_effectif_salarie": null,
                "adresse": "97 B BOULEVARD HENRI BARBUSSE 91210 DRAVEIL",
                "caractere_employeur": "N",
                "cedex": null,
                "code_pays_etranger": null,
                "code_postal": "91210",
                "commune": "91201",
                "complement_adresse": null,
                "coordonnees": "48.685198311,2.4080928697",
                "date_creation": "2012-04-19",
                "date_debut_activite": "2012-04-19",
                "date_fermeture": null,
                "date_mise_a_jour": null,
                "date_mise_a_jour_insee": "2025-12-05T19:52:13",
                "departement": "91",
                "distribution_speciale": null,
                "epci": "200058477",
                "est_siege": true,
                "etat_administratif": "A",
                "geo_adresse": null,
                "geo_id": null,
                "indice_repetition": "B",
                "latitude": "48.685198311",
                "libelle_cedex": null,
                "libelle_commune": "DRAVEIL",
                "libelle_commune_etranger": null,
                "libelle_pays_etranger": null,
                "libelle_voie": "HENRI BARBUSSE",
                "liste_enseignes": null,
                "liste_finess": null,
                "liste_id_bio": null,
                "liste_idcc": null,
                "liste_id_organisme_formation": null,
                "liste_rge": null,
                "liste_uai": null,
                "longitude": "2.4080928697",
                "nom_commercial": null,
                "numero_voie": "97",
                "dernier_numero_voie": null,
                "region": "11",
                "siret": "91054814800014",
                "statut_diffusion_etablissement": "O",
                "tranche_effectif_salarie": "NN",
                "type_voie": "BOULEVARD"
            },
            "activite_principale": "94.20Z",
            "activite_principale_naf25": "94.20Y",
            "categorie_entreprise": "PME",
            "caractere_employeur": null,
            "annee_categorie_entreprise": "2023",
            "date_creation": "2012-04-19",
            "date_fermeture": null,
            "date_mise_a_jour": "2026-06-04T11:18:20",
            "date_mise_a_jour_insee": "2025-12-06T07:52:54",
            "date_mise_a_jour_rne": null,
            "dirigeants": [],
            "etat_administratif": "A",
            "nature_juridique": "8420",
            "section_activite_principale": "S",
            "tranche_effectif_salarie": "NN",
            "annee_tranche_effectif_salarie": null,
            "statut_diffusion": "O",
            "matching_etablissements": [
                {
                    "activite_principale": "94.20Z",
                    "activite_principale_naf25": "94.20Y",
                    "ancien_siege": false,
                    "annee_tranche_effectif_salarie": null,
                    "adresse": "97 B BOULEVARD HENRI BARBUSSE 91210 DRAVEIL",
                    "caractere_employeur": "N",
                    "code_postal": "91210",
                    "commune": "91201",
                    "date_creation": "2012-04-19",
                    "date_debut_activite": "2012-04-19",
                    "date_fermeture": null,
                    "epci": "200058477",
                    "est_siege": true,
                    "etat_administratif": "A",
                    "geo_id": null,
                    "latitude": "48.685198311",
                    "libelle_commune": "DRAVEIL",
                    "liste_enseignes": null,
                    "liste_finess": null,
                    "liste_id_bio": null,
                    "liste_idcc": null,
                    "liste_id_organisme_formation": null,
                    "liste_rge": null,
                    "liste_uai": null,
                    "longitude": "2.4080928697",
                    "nom_commercial": null,
                    "region": "11",
                    "siret": "91054814800014",
                    "statut_diffusion_etablissement": "O",
                    "tranche_effectif_salarie": "NN"
                }
            ],
            "finances": null,
            "complements": {
                "collectivite_territoriale": null,
                "convention_collective_renseignee": false,
                "liste_idcc": null,
                "liste_finess_juridique": null,
                "egapro_renseignee": false,
                "est_achats_responsables": false,
                "est_alim_confiance": false,
                "est_association": false,
                "est_avocat": false,
                "est_bio": false,
                "est_entrepreneur_individuel": false,
                "est_entrepreneur_spectacle": false,
                "est_ess": false,
                "est_finess": false,
                "est_organisme_formation": false,
                "est_qualiopi": false,
                "liste_id_organisme_formation": null,
                "est_rge": false,
                "est_siae": false,
                "est_societe_mission": false,
                "est_uai": false,
                "est_patrimoine_vivant": false,
                "bilan_ges_renseigne": false,
                "identifiant_association": null,
                "statut_entrepreneur_spectacle": null,
                "type_siae": null,
                "a_aide_minimis": false,
                "a_aide_ademe": false,
                "est_administration": false,
                "est_service_public": null,
                "est_l100_3": null
            }
        },
        {
            "siren": "891982050",
            "nom_complet": "SYNDICAT CGT DES FONCTIONNAIRES ET AGENTS TERRITORIAUX ACTIF-VES ET RETRAITE-ES DES ETABLISSEMENTS PUBLICS ET PRIVES DE.",
            "nom_raison_sociale": "SYNDICAT CGT DES FONCTIONNAIRES ET AGENTS TERRITORIAUX ACTIF-VES ET RETRAITE-ES DES ETABLISSEMENTS PUBLICS ET PRIVES DE.",
            "sigle": null,
            "nombre_etablissements": 1,
            "nombre_etablissements_ouverts": 1,
            "siege": {
                "activite_principale": "94.20Z",
                "activite_principale_naf25": "94.20Y",
                "activite_principale_registre_metier": null,
                "annee_tranche_effectif_salarie": null,
                "adresse": "25 RUE JEAN MOULIN 57700 HAYANGE",
                "caractere_employeur": "N",
                "cedex": null,
                "code_pays_etranger": null,
                "code_postal": "57700",
                "commune": "57306",
                "complement_adresse": null,
                "coordonnees": "49.330195368,6.0634571121",
                "date_creation": "2016-01-05",
                "date_debut_activite": "2016-01-05",
                "date_fermeture": null,
                "date_mise_a_jour": null,
                "date_mise_a_jour_insee": "2025-12-06T00:08:46",
                "departement": "57",
                "distribution_speciale": null,
                "epci": "245701222",
                "est_siege": true,
                "etat_administratif": "A",
                "geo_adresse": null,
                "geo_id": null,
                "indice_repetition": null,
                "latitude": "49.330195368",
                "libelle_cedex": null,
                "libelle_commune": "HAYANGE",
                "libelle_commune_etranger": null,
                "libelle_pays_etranger": null,
                "libelle_voie": "JEAN MOULIN",
                "liste_enseignes": null,
                "liste_finess": null,
                "liste_id_bio": null,
                "liste_idcc": null,
                "liste_id_organisme_formation": null,
                "liste_rge": null,
                "liste_uai": null,
                "longitude": "6.0634571121",
                "nom_commercial": null,
                "numero_voie": "25",
                "dernier_numero_voie": null,
                "region": "44",
                "siret": "89198205000017",
                "statut_diffusion_etablissement": "O",
                "tranche_effectif_salarie": "NN",
                "type_voie": "RUE"
            },
            "activite_principale": "94.20Z",
            "activite_principale_naf25": "94.20Y",
            "categorie_entreprise": "PME",
            "caractere_employeur": null,
            "annee_categorie_entreprise": "2023",
            "date_creation": "2016-01-05",
            "date_fermeture": null,
            "date_mise_a_jour": "2026-06-04T11:09:18",
            "date_mise_a_jour_insee": "2025-12-06T08:03:21",
            "date_mise_a_jour_rne": null,
            "dirigeants": [],
            "etat_administratif": "A",
            "nature_juridique": "8410",
            "section_activite_principale": "S",
            "tranche_effectif_salarie": "NN",
            "annee_tranche_effectif_salarie": null,
            "statut_diffusion": "O",
            "matching_etablissements": [
                {
                    "activite_principale": "94.20Z",
                    "activite_principale_naf25": "94.20Y",
                    "ancien_siege": false,
                    "annee_tranche_effectif_salarie": null,
                    "adresse": "25 RUE JEAN MOULIN 57700 HAYANGE",
                    "caractere_employeur": "N",
                    "code_postal": "57700",
                    "commune": "57306",
                    "date_creation": "2016-01-05",
                    "date_debut_activite": "2016-01-05",
                    "date_fermeture": null,
                    "epci": "245701222",
                    "est_siege": true,
                    "etat_administratif": "A",
                    "geo_id": null,
                    "latitude": "49.330195368",
                    "libelle_commune": "HAYANGE",
                    "liste_enseignes": null,
                    "liste_finess": null,
                    "liste_id_bio": null,
                    "liste_idcc": null,
                    "liste_id_organisme_formation": null,
                    "liste_rge": null,
                    "liste_uai": null,
                    "longitude": "6.0634571121",
                    "nom_commercial": null,
                    "region": "44",
                    "siret": "89198205000017",
                    "statut_diffusion_etablissement": "O",
                    "tranche_effectif_salarie": "NN"
                }
            ],
            "finances": null,
            "complements": {
                "collectivite_territoriale": null,
                "convention_collective_renseignee": false,
                "liste_idcc": null,
                "liste_finess_juridique": null,
                "egapro_renseignee": false,
                "est_achats_responsables": false,
                "est_alim_confiance": false,
                "est_association": false,
                "est_avocat": false,
                "est_bio": false,
                "est_entrepreneur_individuel": false,
                "est_entrepreneur_spectacle": false,
                "est_ess": false,
                "est_finess": false,
                "est_organisme_formation": false,
                "est_qualiopi": false,
                "liste_id_organisme_formation": null,
                "est_rge": false,
                "est_siae": false,
                "est_societe_mission": false,
                "est_uai": false,
                "est_patrimoine_vivant": false,
                "bilan_ges_renseigne": false,
                "identifiant_association": null,
                "statut_entrepreneur_spectacle": null,
                "type_siae": null,
                "a_aide_minimis": false,
                "a_aide_ademe": false,
                "est_administration": false,
                "est_service_public": null,
                "est_l100_3": null
            }
        },
        {
            "siren": "924226475",
            "nom_complet": "COORDINATION SYNDICALE DEPARTEMETALE CGT DES SYNDICATS DES PERSONNELS ACTIFS RETRAITES DES SERVICES PUBLICS DU VAUCLUSE",
            "nom_raison_sociale": "COORDINATION SYNDICALE DEPARTEMETALE CGT DES SYNDICATS DES PERSONNELS ACTIFS RETRAITES DES SERVICES PUBLICS DU VAUCLUSE",
            "sigle": null,
            "nombre_etablissements": 1,
            "nombre_etablissements_ouverts": 1,
            "siege": {
                "activite_principale": "94.20Z",
                "activite_principale_naf25": "94.20Y",
                "activite_principale_registre_metier": null,
                "annee_tranche_effectif_salarie": null,
                "adresse": "BAT LE CONSULAT - VAULUSE VILLAGE 164 AVENUE DE SAINT TRONQUET 84130 LE PONTET",
                "caractere_employeur": "N",
                "cedex": null,
                "code_pays_etranger": null,
                "code_postal": "84130",
                "commune": "84092",
                "complement_adresse": "BAT LE CONSULAT - VAULUSE VILLAGE",
                "coordonnees": "43.9801215485773,4.87425138137279",
                "date_creation": "2020-11-19",
                "date_debut_activite": "2020-11-19",
                "date_fermeture": null,
                "date_mise_a_jour": null,
                "date_mise_a_jour_insee": "2025-12-05T23:04:37",
                "departement": "84",
                "distribution_speciale": null,
                "epci": "248400251",
                "est_siege": true,
                "etat_administratif": "A",
                "geo_adresse": null,
                "geo_id": null,
                "indice_repetition": null,
                "latitude": "43.9801215485773",
                "libelle_cedex": null,
                "libelle_commune": "LE PONTET",
                "libelle_commune_etranger": null,
                "libelle_pays_etranger": null,
                "libelle_voie": "DE SAINT TRONQUET",
                "liste_enseignes": null,
                "liste_finess": null,
                "liste_id_bio": null,
                "liste_idcc": null,
                "liste_id_organisme_formation": null,
                "liste_rge": null,
                "liste_uai": null,
                "longitude": "4.87425138137279",
                "nom_commercial": null,
                "numero_voie": "164",
                "dernier_numero_voie": null,
                "region": "93",
                "siret": "92422647500011",
                "statut_diffusion_etablissement": "O",
                "tranche_effectif_salarie": "NN",
                "type_voie": "AVENUE"
            },
            "activite_principale": "94.20Z",
            "activite_principale_naf25": "94.20Y",
            "categorie_entreprise": null,
            "caractere_employeur": null,
            "annee_categorie_entreprise": null,
            "date_creation": "2020-11-19",
            "date_fermeture": null,
            "date_mise_a_jour": "2026-06-04T11:25:27",
            "date_mise_a_jour_insee": "2025-12-06T06:32:14",
            "date_mise_a_jour_rne": null,
            "dirigeants": [],
            "etat_administratif": "A",
            "nature_juridique": "8410",
            "section_activite_principale": "S",
            "tranche_effectif_salarie": "NN",
            "annee_tranche_effectif_salarie": null,
            "statut_diffusion": "O",
            "matching_etablissements": [
                {
                    "activite_principale": "94.20Z",
                    "activite_principale_naf25": "94.20Y",
                    "ancien_siege": false,
                    "annee_tranche_effectif_salarie": null,
                    "adresse": "BAT LE CONSULAT - VAULUSE VILLAGE 164 AVENUE DE SAINT TRONQUET 84130 LE PONTET",
                    "caractere_employeur": "N",
                    "code_postal": "84130",
                    "commune": "84092",
                    "date_creation": "2020-11-19",
                    "date_debut_activite": "2020-11-19",
                    "date_fermeture": null,
                    "epci": "248400251",
                    "est_siege": true,
                    "etat_administratif": "A",
                    "geo_id": null,
                    "latitude": "43.9801215485773",
                    "libelle_commune": "LE PONTET",
                    "liste_enseignes": null,
                    "liste_finess": null,
                    "liste_id_bio": null,
                    "liste_idcc": null,
                    "liste_id_organisme_formation": null,
                    "liste_rge": null,
                    "liste_uai": null,
                    "longitude": "4.87425138137279",
                    "nom_commercial": null,
                    "region": "93",
                    "siret": "92422647500011",
                    "statut_diffusion_etablissement": "O",
                    "tranche_effectif_salarie": "NN"
                }
            ],
            "finances": null,
            "complements": {
                "collectivite_territoriale": null,
                "convention_collective_renseignee": false,
                "liste_idcc": null,
                "liste_finess_juridique": null,
                "egapro_renseignee": false,
                "est_achats_responsables": false,
                "est_alim_confiance": false,
                "est_association": false,
                "est_avocat": false,
                "est_bio": false,
                "est_entrepreneur_individuel": false,
                "est_entrepreneur_spectacle": false,
                "est_ess": false,
                "est_finess": false,
                "est_organisme_formation": false,
                "est_qualiopi": false,
                "liste_id_organisme_formation": null,
                "est_rge": false,
                "est_siae": false,
                "est_societe_mission": false,
                "est_uai": false,
                "est_patrimoine_vivant": false,
                "bilan_ges_renseigne": false,
                "identifiant_association": null,
                "statut_entrepreneur_spectacle": null,
                "type_siae": null,
                "a_aide_minimis": false,
                "a_aide_ademe": false,
                "est_administration": false,
                "est_service_public": null,
                "est_l100_3": null
            }
        },
        {
            "siren": "942539594",
            "nom_complet": "SYNDICAT CGT FONCTIONNAIRES ET AGENTS TERRITX ACTIFS ET RETRAITES DES ETABL PUBLICS ET PRIVES DE L'ARGONNE ARDENNAISE",
            "nom_raison_sociale": "SYNDICAT CGT FONCTIONNAIRES ET AGENTS TERRITX ACTIFS ET RETRAITES DES ETABL PUBLICS ET PRIVES DE L'ARGONNE ARDENNAISE",
            "sigle": null,
            "nombre_etablissements": 1,
            "nombre_etablissements_ouverts": 1,
            "siege": {
                "activite_principale": "94.20Z",
                "activite_principale_naf25": "94.20Y",
                "activite_principale_registre_metier": null,
                "annee_tranche_effectif_salarie": null,
                "adresse": "6 PLACE CARNOT 08400 VOUZIERS",
                "caractere_employeur": "N",
                "cedex": null,
                "code_pays_etranger": null,
                "code_postal": "08400",
                "commune": "08490",
                "complement_adresse": null,
                "coordonnees": "49.3979722137076,4.69986283612035",
                "date_creation": "2021-01-13",
                "date_debut_activite": "2021-01-13",
                "date_fermeture": null,
                "date_mise_a_jour": null,
                "date_mise_a_jour_insee": "2025-12-06T03:31:36",
                "departement": "08",
                "distribution_speciale": null,
                "epci": "240800920",
                "est_siege": true,
                "etat_administratif": "A",
                "geo_adresse": null,
                "geo_id": null,
                "indice_repetition": null,
                "latitude": "49.3979722137076",
                "libelle_cedex": null,
                "libelle_commune": "VOUZIERS",
                "libelle_commune_etranger": null,
                "libelle_pays_etranger": null,
                "libelle_voie": "CARNOT",
                "liste_enseignes": null,
                "liste_finess": null,
                "liste_id_bio": null,
                "liste_idcc": null,
                "liste_id_organisme_formation": null,
                "liste_rge": null,
                "liste_uai": null,
                "longitude": "4.69986283612035",
                "nom_commercial": null,
                "numero_voie": "6",
                "dernier_numero_voie": null,
                "region": "44",
                "siret": "94253959400013",
                "statut_diffusion_etablissement": "O",
                "tranche_effectif_salarie": "NN",
                "type_voie": "PLACE"
            },
            "activite_principale": "94.20Z",
            "activite_principale_naf25": "94.20Y",
            "categorie_entreprise": null,
            "caractere_employeur": null,
            "annee_categorie_entreprise": null,
            "date_creation": "2021-01-13",
            "date_fermeture": null,
            "date_mise_a_jour": "2026-06-04T11:33:17",
            "date_mise_a_jour_insee": "2025-12-06T08:59:29",
            "date_mise_a_jour_rne": null,
            "dirigeants": [],
            "etat_administratif": "A",
            "nature_juridique": "8410",
            "section_activite_principale": "S",
            "tranche_effectif_salarie": "NN",
            "annee_tranche_effectif_salarie": null,
            "statut_diffusion": "O",
            "matching_etablissements": [
                {
                    "activite_principale": "94.20Z",
                    "activite_principale_naf25": "94.20Y",
                    "ancien_siege": false,
                    "annee_tranche_effectif_salarie": null,
                    "adresse": "6 PLACE CARNOT 08400 VOUZIERS",
                    "caractere_employeur": "N",
                    "code_postal": "08400",
                    "commune": "08490",
                    "date_creation": "2021-01-13",
                    "date_debut_activite": "2021-01-13",
                    "date_fermeture": null,
                    "epci": "240800920",
                    "est_siege": true,
                    "etat_administratif": "A",
                    "geo_id": null,
                    "latitude": "49.3979722137076",
                    "libelle_commune": "VOUZIERS",
                    "liste_enseignes": null,
                    "liste_finess": null,
                    "liste_id_bio": null,
                    "liste_idcc": null,
                    "liste_id_organisme_formation": null,
                    "liste_rge": null,
                    "liste_uai": null,
                    "longitude": "4.69986283612035",
                    "nom_commercial": null,
                    "region": "44",
                    "siret": "94253959400013",
                    "statut_diffusion_etablissement": "O",
                    "tranche_effectif_salarie": "NN"
                }
            ],
            "finances": null,
            "complements": {
                "collectivite_territoriale": null,
                "convention_collective_renseignee": false,
                "liste_idcc": null,
                "liste_finess_juridique": null,
                "egapro_renseignee": false,
                "est_achats_responsables": false,
                "est_alim_confiance": false,
                "est_association": false,
                "est_avocat": false,
                "est_bio": false,
                "est_entrepreneur_individuel": false,
                "est_entrepreneur_spectacle": false,
                "est_ess": false,
                "est_finess": false,
                "est_organisme_formation": false,
                "est_qualiopi": false,
                "liste_id_organisme_formation": null,
                "est_rge": false,
                "est_siae": false,
                "est_societe_mission": false,
                "est_uai": false,
                "est_patrimoine_vivant": false,
                "bilan_ges_renseigne": false,
                "identifiant_association": null,
                "statut_entrepreneur_spectacle": null,
                "type_siae": null,
                "a_aide_minimis": false,
                "a_aide_ademe": false,
                "est_administration": false,
                "est_service_public": null,
                "est_l100_3": null
            }
        }
    ],
    "total_results": 16,
    "page": 1,
    "per_page": 10,
    "total_pages": 2
}